{
    "swagger": "2.0",
    "info": {
        "version": "1.0.0",
        "title": "EpiOpera API Documentation",
        "description": "EpiOpera API Documentation",
        "license": {
            "name": "MIT",
            "url": "https://opensource.org/licenses/MIT"
        }
    },
    "host": "localhost:8080",
    "basepath": "/",
    "schemes": [
        "http"
    ],
    "consumes": [
        "application/json"
    ],
    "produces": [
        "application/json"
    ],
    "paths": {
        "/user": {
            "get": {
                "tags": [
                    "Users"
                ],
                "summary": "Get all users in system",
                "responses": {
                    "200": {
                        "description": "OK",
                        "schema": {
                            "$ref": "#/definitions/User"
                        }
                    }
                }
            },
            "post": {
                "tags": [
                    "Users"
                ],
                "summary": "Post a new user",
                "parameters": [
                    {
                        "name": "body",
                        "in": "body",
                        "description": "Body of user post API",
                        "required": true,
                        "schema": {
                            "$ref": "#/definitions/User"
                        }
                    }
                ],
                "responses": {
                    "200": {
                        "description": "OK",
                        "schema": {
                            "$ref": "#/definitions/User"
                        }
                    },
                    "400": {
                        "description": "Invalid input"
                    },
                    "500": {
                        "description": "Internal server error"
                    }
                }
            }
        },
        "/user/{username}": {
            "delete": {
                "tags": [
                    "Users"
                ],
                "summary": "Deletes a user by username",
                "parameters": [
                    {
                        "name": "username",
                        "in": "path",
                        "description": "Username of user to delete",
                        "required": true,
                        "schema": {
                            "type": "string"
                        }
                    }
                ],
                "responses": {
                    "400": {
                        "description": "Invalid User Id"
                    },
                    "404": {
                        "description": "User not found"
                    }
                }
            }
        },
        "/post": {
            "get": {
                "tags": [
                    "Posts"
                ],
                "summary": "Get all posts in system",
                "responses": {
                    "200": {
                        "description": "OK",
                        "schema": {
                            "$ref": "#/definitions/Post"
                        }
                    }
                }
            },
            "post": {
                "tags": [
                    "Posts"
                ],
                "summary": "Post a new user",
                "parameters": [
                    {
                        "name": "body",
                        "in": "body",
                        "description": "Body of post post API",
                        "required": true,
                        "schema": {
                            "$ref": "#/definitions/Post"
                        }
                    }
                ],
                "responses": {
                    "200": {
                        "description": "OK",
                        "schema": {
                            "$ref": "#/definitions/Post"
                        }
                    },
                    "400": {
                        "description": "Invalid input"
                    },
                    "500": {
                        "description": "Internal server error"
                    }
                }
            }
        },
        "/post/{id}": {
            "delete": {
                "tags": [
                    "Posts"
                ],
                "summary": "Deletes a post bi id",
                "parameters": [
                    {
                        "name": "id",
                        "in": "path",
                        "description": "Id of post to delete",
                        "required": true,
                        "schema": {
                            "type": "string"
                        }
                    }
                ],
                "responses": {
                    "400": {
                        "description": "Invalid username"
                    },
                    "404": {
                        "description": "Post not found"
                    }
                }
            }
        }
    },
    "definitions": {
        "User": {
            "required": [
                "username"
            ],
            "properties": {
                "username": {
                    "type": "string"
                },
                "email": {
                    "type": "string",
                    "example": "user@something.domain"
                },
                "psw": {
                    "type": "string"
                },
                "nsfwIconFlag": {
                    "type": "boolean"
                },
                "nsfwBannerFlag": {
                    "type": "boolean"
                },
                "lingua": {
                    "type": "string",
                    "enum": [
                        "italiano",
                        "inglese"
                    ]
                },
                "nsfwSetting": {
                    "type": "string",
                    "enum": [
                        "no",
                        "blur",
                        "yes"
                    ]
                },
                "followed_users": {
                    "type": "array",
                    "items": {
                        "type": "number"
                    }
                },
                "favourites": {
                    "type": "array",
                    "items": {
                        "type": "number"
                    }
                }
            }
        },
        "Post": {
            "required": [
                "id"
            ],
            "properties": {
                "id": {
                    "type": "number"
                },
                "title": {
                    "type": "string"
                },
                "date": {
                    "type": "string"
                },
                "text": {
                    "type": "string"
                },
                "media": {
                    "type": "string"
                },
                "tag": {
                    "type": "array",
                    "items": {
                        "type": "string"
                    }
                },
                "punteggio_post": {
                    "type": "number"
                },
                "segnalato": {
                    "type": "boolean"
                },
                "numero_commenti": {
                    "type": "number"
                },
                "associato_a_contest": {
                    "type": "array",
                    "items": {
                        "type": "number"
                    }
                },
                "creatore_post": {
                    "type": "string"
                }
            }
        }
    }
}